{"nodes": [{"id": "mainactivity_kt", "label": "MainActivity", "file_type": "code", "source_file": "ui/mobile-android/app/src/main/java/com/sebastian/android/MainActivity.kt", "source_location": null, "source_url": null, "captured_at": null, "author": null, "contributor": null}, {"id": "sebastiannavhost", "label": "SebastianNavHost (Composable)", "file_type": "code", "source_file": "ui/mobile-android/app/src/main/java/com/sebastian/android/MainActivity.kt", "source_location": "L72", "source_url": null, "captured_at": null, "author": null, "contributor": null}], "edges": [{"source": "mainactivity_kt", "target": "sebastiannavhost", "relation": "calls", "confidence": "EXTRACTED", "confidence_score": 1.0, "source_file": "ui/mobile-android/app/src/main/java/com/sebastian/android/MainActivity.kt", "source_location": "L65", "weight": 1.0}, {"source": "mainactivity_kt", "target": "settingsdatastore", "relation": "references", "confidence": "EXTRACTED", "confidence_score": 1.0, "source_file": "ui/mobile-android/app/src/main/java/com/sebastian/android/MainActivity.kt", "source_location": "L52", "weight": 1.0}, {"source": "sebastiannavhost", "target": "globalapprovalviewmodel_kt", "relation": "calls", "confidence": "EXTRACTED", "confidence_score": 1.0, "source_file": "ui/mobile-android/app/src/main/java/com/sebastian/android/MainActivity.kt", "source_location": "L74", "weight": 1.0}, {"source": "sebastiannavhost", "target": "globalapprovalbanner", "relation": "calls", "confidence": "EXTRACTED", "confidence_score": 1.0, "source_file": "ui/mobile-android/app/src/main/java/com/sebastian/android/MainActivity.kt", "source_location": "L151", "weight": 1.0}, {"source": "sebastiannavhost", "target": "route_navigation", "relation": "references", "confidence": "EXTRACTED", "confidence_score": 1.0, "source_file": "ui/mobile-android/app/src/main/java/com/sebastian/android/MainActivity.kt", "source_location": "L94", "weight": 1.0}, {"source": "sebastiannavhost", "target": "settingsscreen_kt", "relation": "calls", "confidence": "EXTRACTED", "confidence_score": 1.0, "source_file": "ui/mobile-android/app/src/main/java/com/sebastian/android/MainActivity.kt", "source_location": "L127", "weight": 1.0}, {"source": "sebastiannavhost", "target": "providerformpage_kt", "relation": "calls", "confidence": "EXTRACTED", "confidence_score": 1.0, "source_file": "ui/mobile-android/app/src/main/java/com/sebastian/android/MainActivity.kt", "source_location": "L142", "weight": 1.0}], "hyperedges": [{"id": "approval_flow", "label": "Global Approval Flow: GlobalApprovalViewModel \u2192 GlobalApprovalBanner \u2192 ChatRepository", "nodes": ["globalapprovalviewmodel_kt", "globalapprovalbanner", "chatrepository"], "relation": "implement", "confidence": "EXTRACTED", "confidence_score": 0.9, "source_file": "ui/mobile-android/app/src/main/java/com/sebastian/android/MainActivity.kt"}]}