{"nodes": [{"id": "tests_unit_test_base_agent_py", "label": "test_base_agent.py", "file_type": "code", "source_file": "tests/unit/test_base_agent.py", "source_location": "L1"}, {"id": "test_base_agent_test_base_agent_persists_user_turn_before_inference_failure", "label": "test_base_agent_persists_user_turn_before_inference_failure()", "file_type": "code", "source_file": "tests/unit/test_base_agent.py", "source_location": "L11"}, {"id": "test_base_agent_test_base_agent_writes_messages_to_overridden_agent_context", "label": "test_base_agent_writes_messages_to_overridden_agent_context()", "file_type": "code", "source_file": "tests/unit/test_base_agent.py", "source_location": "L47"}, {"id": "test_base_agent_test_run_streaming_publishes_turn_events", "label": "test_run_streaming_publishes_turn_events()", "file_type": "code", "source_file": "tests/unit/test_base_agent.py", "source_location": "L94"}, {"id": "test_base_agent_test_base_agent_run_streaming_passes_thinking_effort_to_loop", "label": "test_base_agent_run_streaming_passes_thinking_effort_to_loop()", "file_type": "code", "source_file": "tests/unit/test_base_agent.py", "source_location": "L152"}, {"id": "test_base_agent_test_run_streaming_interrupt_publishes_interrupted", "label": "test_run_streaming_interrupt_publishes_interrupted()", "file_type": "code", "source_file": "tests/unit/test_base_agent.py", "source_location": "L188"}, {"id": "test_base_agent_test_base_agent_has_no_execute_delegated_task", "label": "test_base_agent_has_no_execute_delegated_task()", "file_type": "code", "source_file": "tests/unit/test_base_agent.py", "source_location": "L246"}, {"id": "test_base_agent_test_build_system_prompt_contains_guidelines_section", "label": "test_build_system_prompt_contains_guidelines_section()", "file_type": "code", "source_file": "tests/unit/test_base_agent.py", "source_location": "L253"}, {"id": "test_base_agent_test_guidelines_section_appears_before_tools_section", "label": "test_guidelines_section_appears_before_tools_section()", "file_type": "code", "source_file": "tests/unit/test_base_agent.py", "source_location": "L284"}, {"id": "test_base_agent_test_cancel_session_returns_false_when_no_active_stream", "label": "test_cancel_session_returns_false_when_no_active_stream()", "file_type": "code", "source_file": "tests/unit/test_base_agent.py", "source_location": "L316"}, {"id": "test_base_agent_test_cancel_session_cancels_active_stream", "label": "test_cancel_session_cancels_active_stream()", "file_type": "code", "source_file": "tests/unit/test_base_agent.py", "source_location": "L335"}, {"id": "test_base_agent_test_cancel_session_flushes_partial_text_to_episodic", "label": "test_cancel_session_flushes_partial_text_to_episodic()", "file_type": "code", "source_file": "tests/unit/test_base_agent.py", "source_location": "L373"}, {"id": "test_base_agent_test_cancel_session_skips_flush_when_no_partial", "label": "test_cancel_session_skips_flush_when_no_partial()", "file_type": "code", "source_file": "tests/unit/test_base_agent.py", "source_location": "L414"}, {"id": "test_base_agent_test_cancel_session_emits_turn_cancelled_and_turn_response", "label": "test_cancel_session_emits_turn_cancelled_and_turn_response()", "file_type": "code", "source_file": "tests/unit/test_base_agent.py", "source_location": "L451"}, {"id": "test_base_agent_test_cancel_session_idempotent", "label": "test_cancel_session_idempotent()", "file_type": "code", "source_file": "tests/unit/test_base_agent.py", "source_location": "L497"}, {"id": "test_base_agent_test_cancel_session_no_memory_leak_in_buffers", "label": "test_cancel_session_no_memory_leak_in_buffers()", "file_type": "code", "source_file": "tests/unit/test_base_agent.py", "source_location": "L534"}, {"id": "test_base_agent_rationale_247", "label": "execute_delegated_task should be removed.", "file_type": "rationale", "source_file": "tests/unit/test_base_agent.py", "source_location": "L247"}, {"id": "test_base_agent_rationale_254", "label": "build_system_prompt() \u5305\u542b guidelines section\uff0c\u542b workspace_dir \u8def\u5f84\u3002", "file_type": "rationale", "source_file": "tests/unit/test_base_agent.py", "source_location": "L254"}, {"id": "test_base_agent_rationale_285", "label": "guidelines section \u5fc5\u987b\u5728 tools section \u4e4b\u524d\u51fa\u73b0\u3002", "file_type": "rationale", "source_file": "tests/unit/test_base_agent.py", "source_location": "L285"}, {"id": "test_base_agent_rationale_317", "label": "Cancelling an idle session returns False \u2014 no stream to cancel.", "file_type": "rationale", "source_file": "tests/unit/test_base_agent.py", "source_location": "L317"}, {"id": "test_base_agent_rationale_336", "label": "cancel_session() cancels a long-running stream and clears _active_streams.", "file_type": "rationale", "source_file": "tests/unit/test_base_agent.py", "source_location": "L336"}, {"id": "test_base_agent_rationale_374", "label": "Partial text is saved to episodic memory with [\u7528\u6237\u4e2d\u65ad] suffix on cancel.", "file_type": "rationale", "source_file": "tests/unit/test_base_agent.py", "source_location": "L374"}, {"id": "test_base_agent_rationale_415", "label": "If no text was emitted before cancel, no assistant message is written.", "file_type": "rationale", "source_file": "tests/unit/test_base_agent.py", "source_location": "L415"}, {"id": "test_base_agent_rationale_452", "label": "cancel_session emits TURN_CANCELLED then TURN_RESPONSE on the event bus.", "file_type": "rationale", "source_file": "tests/unit/test_base_agent.py", "source_location": "L452"}, {"id": "test_base_agent_rationale_498", "label": "Second cancel call on same session returns False and does not raise.", "file_type": "rationale", "source_file": "tests/unit/test_base_agent.py", "source_location": "L498"}, {"id": "test_base_agent_rationale_535", "label": "After cancel, _cancel_requested and _partial_buffer are cleaned up.", "file_type": "rationale", "source_file": "tests/unit/test_base_agent.py", "source_location": "L535"}], "edges": [{"source": "tests_unit_test_base_agent_py", "target": "asyncio", "relation": "imports", "confidence": "EXTRACTED", "source_file": "tests/unit/test_base_agent.py", "source_location": "L3", "weight": 1.0}, {"source": "tests_unit_test_base_agent_py", "target": "pathlib", "relation": "imports_from", "confidence": "EXTRACTED", "source_file": "tests/unit/test_base_agent.py", "source_location": "L4", "weight": 1.0}, {"source": "tests_unit_test_base_agent_py", "target": "unittest_mock", "relation": "imports_from", "confidence": "EXTRACTED", "source_file": "tests/unit/test_base_agent.py", "source_location": "L5", "weight": 1.0}, {"source": "tests_unit_test_base_agent_py", "target": "pytest", "relation": "imports", "confidence": "EXTRACTED", "source_file": "tests/unit/test_base_agent.py", "source_location": "L7", "weight": 1.0}, {"source": "tests_unit_test_base_agent_py", "target": "test_base_agent_test_base_agent_persists_user_turn_before_inference_failure", "relation": "contains", "confidence": "EXTRACTED", "source_file": "tests/unit/test_base_agent.py", "source_location": "L11", "weight": 1.0}, {"source": "tests_unit_test_base_agent_py", "target": "test_base_agent_test_base_agent_writes_messages_to_overridden_agent_context", "relation": "contains", "confidence": "EXTRACTED", "source_file": "tests/unit/test_base_agent.py", "source_location": "L47", "weight": 1.0}, {"source": "tests_unit_test_base_agent_py", "target": "test_base_agent_test_run_streaming_publishes_turn_events", "relation": "contains", "confidence": "EXTRACTED", "source_file": "tests/unit/test_base_agent.py", "source_location": "L94", "weight": 1.0}, {"source": "tests_unit_test_base_agent_py", "target": "test_base_agent_test_base_agent_run_streaming_passes_thinking_effort_to_loop", "relation": "contains", "confidence": "EXTRACTED", "source_file": "tests/unit/test_base_agent.py", "source_location": "L152", "weight": 1.0}, {"source": "tests_unit_test_base_agent_py", "target": "test_base_agent_test_run_streaming_interrupt_publishes_interrupted", "relation": "contains", "confidence": "EXTRACTED", "source_file": "tests/unit/test_base_agent.py", "source_location": "L188", "weight": 1.0}, {"source": "tests_unit_test_base_agent_py", "target": "test_base_agent_test_base_agent_has_no_execute_delegated_task", "relation": "contains", "confidence": "EXTRACTED", "source_file": "tests/unit/test_base_agent.py", "source_location": "L246", "weight": 1.0}, {"source": "tests_unit_test_base_agent_py", "target": "test_base_agent_test_build_system_prompt_contains_guidelines_section", "relation": "contains", "confidence": "EXTRACTED", "source_file": "tests/unit/test_base_agent.py", "source_location": "L253", "weight": 1.0}, {"source": "tests_unit_test_base_agent_py", "target": "test_base_agent_test_guidelines_section_appears_before_tools_section", "relation": "contains", "confidence": "EXTRACTED", "source_file": "tests/unit/test_base_agent.py", "source_location": "L284", "weight": 1.0}, {"source": "tests_unit_test_base_agent_py", "target": "test_base_agent_test_cancel_session_returns_false_when_no_active_stream", "relation": "contains", "confidence": "EXTRACTED", "source_file": "tests/unit/test_base_agent.py", "source_location": "L316", "weight": 1.0}, {"source": "tests_unit_test_base_agent_py", "target": "test_base_agent_test_cancel_session_cancels_active_stream", "relation": "contains", "confidence": "EXTRACTED", "source_file": "tests/unit/test_base_agent.py", "source_location": "L335", "weight": 1.0}, {"source": "tests_unit_test_base_agent_py", "target": "test_base_agent_test_cancel_session_flushes_partial_text_to_episodic", "relation": "contains", "confidence": "EXTRACTED", "source_file": "tests/unit/test_base_agent.py", "source_location": "L373", "weight": 1.0}, {"source": "tests_unit_test_base_agent_py", "target": "test_base_agent_test_cancel_session_skips_flush_when_no_partial", "relation": "contains", "confidence": "EXTRACTED", "source_file": "tests/unit/test_base_agent.py", "source_location": "L414", "weight": 1.0}, {"source": "tests_unit_test_base_agent_py", "target": "test_base_agent_test_cancel_session_emits_turn_cancelled_and_turn_response", "relation": "contains", "confidence": "EXTRACTED", "source_file": "tests/unit/test_base_agent.py", "source_location": "L451", "weight": 1.0}, {"source": "tests_unit_test_base_agent_py", "target": "test_base_agent_test_cancel_session_idempotent", "relation": "contains", "confidence": "EXTRACTED", "source_file": "tests/unit/test_base_agent.py", "source_location": "L497", "weight": 1.0}, {"source": "tests_unit_test_base_agent_py", "target": "test_base_agent_test_cancel_session_no_memory_leak_in_buffers", "relation": "contains", "confidence": "EXTRACTED", "source_file": "tests/unit/test_base_agent.py", "source_location": "L534", "weight": 1.0}, {"source": "test_base_agent_rationale_247", "target": "test_base_agent_test_base_agent_has_no_execute_delegated_task", "relation": "rationale_for", "confidence": "EXTRACTED", "source_file": "tests/unit/test_base_agent.py", "source_location": "L247", "weight": 1.0}, {"source": "test_base_agent_rationale_254", "target": "test_base_agent_test_build_system_prompt_contains_guidelines_section", "relation": "rationale_for", "confidence": "EXTRACTED", "source_file": "tests/unit/test_base_agent.py", "source_location": "L254", "weight": 1.0}, {"source": "test_base_agent_rationale_285", "target": "test_base_agent_test_guidelines_section_appears_before_tools_section", "relation": "rationale_for", "confidence": "EXTRACTED", "source_file": "tests/unit/test_base_agent.py", "source_location": "L285", "weight": 1.0}, {"source": "test_base_agent_rationale_317", "target": "test_base_agent_test_cancel_session_returns_false_when_no_active_stream", "relation": "rationale_for", "confidence": "EXTRACTED", "source_file": "tests/unit/test_base_agent.py", "source_location": "L317", "weight": 1.0}, {"source": "test_base_agent_rationale_336", "target": "test_base_agent_test_cancel_session_cancels_active_stream", "relation": "rationale_for", "confidence": "EXTRACTED", "source_file": "tests/unit/test_base_agent.py", "source_location": "L336", "weight": 1.0}, {"source": "test_base_agent_rationale_374", "target": "test_base_agent_test_cancel_session_flushes_partial_text_to_episodic", "relation": "rationale_for", "confidence": "EXTRACTED", "source_file": "tests/unit/test_base_agent.py", "source_location": "L374", "weight": 1.0}, {"source": "test_base_agent_rationale_415", "target": "test_base_agent_test_cancel_session_skips_flush_when_no_partial", "relation": "rationale_for", "confidence": "EXTRACTED", "source_file": "tests/unit/test_base_agent.py", "source_location": "L415", "weight": 1.0}, {"source": "test_base_agent_rationale_452", "target": "test_base_agent_test_cancel_session_emits_turn_cancelled_and_turn_response", "relation": "rationale_for", "confidence": "EXTRACTED", "source_file": "tests/unit/test_base_agent.py", "source_location": "L452", "weight": 1.0}, {"source": "test_base_agent_rationale_498", "target": "test_base_agent_test_cancel_session_idempotent", "relation": "rationale_for", "confidence": "EXTRACTED", "source_file": "tests/unit/test_base_agent.py", "source_location": "L498", "weight": 1.0}, {"source": "test_base_agent_rationale_535", "target": "test_base_agent_test_cancel_session_no_memory_leak_in_buffers", "relation": "rationale_for", "confidence": "EXTRACTED", "source_file": "tests/unit/test_base_agent.py", "source_location": "L535", "weight": 1.0}]}